pepsin/__init__.py
pepsin/base.py
pepsin/base_io.py
pepsin/config.py
pepsin/const.py
pepsin/error.py
pepsin/main.py
pepsin/pyhandler.py
pepsin/template.py
pepsin/version.py
pepsin/yml.py
pepsin/commands/__init__.py
pepsin/commands/add.py
pepsin/commands/i.py
pepsin/commands/init.py
pepsin/commands/install.py
pepsin/commands/pip.py
pepsin/commands/uninstall.py
pepsin/commands/update.py
pepsin/commands/upgrade.py
pepsin/templates/.gitignore
pepsin/templates/Readme.MD
pepsin/templates/__init__.py
pepsin/utils/__init__.py
pepsin/utils/base.py
pepsin/utils/spinner.py
test/__init__.py
test/test_config.py
test/test_io.py
test/test_prompt.py
test/test_py_handler.py
test/test_schema.py
test/test_template.py
test/test_utils.py
test/test_yaml.py
test/utils.py
test/commands/__init__.py
test/commands/test_base.py
test/commands/test_cli.py
test/commands/test_init.py
test/commands/test_install.py
test/commands/test_install_fail.py
test/commands/test_pip.py
test/commands/test_uninstall.py
test/commands/test_upgrade.py
test/commands/temp/__init__.py
test/temp/__init__.py
pepsin-1.0.0b0.dist-info/METADATA
pepsin-1.0.0b0.dist-info/WHEEL
pepsin-1.0.0b0.dist-info/entry_points.txt
pepsin-1.0.0b0.dist-info/top_level.txt
pepsin-1.0.0b0.dist-info/RECORD
