Metadata-Version: 2.1
Name: pepsin
Version: 1.0.0b0
Summary: Python PIP Toolchain cli
Home-page: UNKNOWN
Author: Khan Asfi Reza
Author-email: khanasfireza10@gmail.com
License: UNKNOWN
Platform: UNKNOWN
Classifier: Programming Language :: Python :: 3
Classifier: License :: OSI Approved :: MIT License
Classifier: Operating System :: OS Independent
Requires-Python: >=3.6
Requires-Dist: PyYAML
Requires-Dist: colorama
Requires-Dist: virtualenv
